MANIFEST.in
README.md
pyproject.toml
setup.py
wormcat3/__init__.py
wormcat3/annotations_manger.py
wormcat3/bubble_chart.py
wormcat3/constants.py
wormcat3/file_util.py
wormcat3/gsea_analyzer.py
wormcat3/statistical_analysis.py
wormcat3/sunburst.py
wormcat3/sunburst_template.py
wormcat3/wormcat.py
wormcat3/wormcat_error.py
wormcat3/wormcat_excel.py
wormcat3.egg-info/PKG-INFO
wormcat3.egg-info/SOURCES.txt
wormcat3.egg-info/dependency_links.txt
wormcat3.egg-info/not-zip-safe
wormcat3.egg-info/requires.txt
wormcat3.egg-info/top_level.txt
wormcat3/extdata/ORF_only_v2_nov-11-2021.csv
wormcat3/extdata/ahringer_v2_nov-11-2021.csv
wormcat3/extdata/orfeome_v2_nov-11-2021.csv
wormcat3/extdata/whole_genome_v2_nov-11-2021.csv