Metadata-Version: 2.2
Name: wormcat3
Version: 0.1.5
Summary: WormCat is a tool for annotating and visualizing gene set enrichment data from C. elegans microarray, RNA seq or RNAi screen data.
Home-page: https://github.com/DanHUMassMed/wormcat3.git
Author: Dan Higgins
Author-email: daniel.higgins@gatech.edu
License: MIT
Requires-Dist: ipykernel
Requires-Dist: scipy==1.15.2
Requires-Dist: pandas==2.2.3
Requires-Dist: gseapy==1.1.8
Requires-Dist: plotnine==0.14.5
Requires-Dist: statsmodels==0.14.4
Requires-Dist: XlsxWriter==3.2.2
Requires-Dist: openpyxl==3.1.5
Dynamic: author
Dynamic: author-email
Dynamic: description
Dynamic: description-content-type
Dynamic: home-page
Dynamic: license
Dynamic: requires-dist
Dynamic: summary
